topsis_package/__init__.py
topsis_package/__main__.py
topsis_package/core.py
topsis_vidyt_102303747-1.0.2.dist-info/licenses/LICENSE
topsis_vidyt_102303747-1.0.2.dist-info/METADATA
topsis_vidyt_102303747-1.0.2.dist-info/WHEEL
topsis_vidyt_102303747-1.0.2.dist-info/entry_points.txt
topsis_vidyt_102303747-1.0.2.dist-info/top_level.txt
topsis_vidyt_102303747-1.0.2.dist-info/RECORD
