Metadata-Version: 2.4
Name: topsis-vidyt-102303747
Version: 1.0.2
Summary: TOPSIS (Technique for Order of Preference by Similarity to Ideal Solution) implementation for multi-criteria decision making
Home-page: https://github.com/VidytBhudolia/UCS654-102303747
Author: Vidyt
Author-email: Vidyt <vidyt102303747@example.com>
License: MIT
Project-URL: Homepage, https://github.com/VidytBhudolia/UCS654-102303747
Project-URL: Documentation, https://github.com/VidytBhudolia/UCS654-102303747/blob/main/README.md
Project-URL: Repository, https://github.com/VidytBhudolia/UCS654-102303747.git
Project-URL: Bug Tracker, https://github.com/VidytBhudolia/UCS654-102303747/issues
Keywords: topsis,decision-making,multi-criteria,ranking
Classifier: Development Status :: 4 - Beta
Classifier: Intended Audience :: Developers
Classifier: Intended Audience :: Science/Research
Classifier: License :: OSI Approved :: MIT License
Classifier: Programming Language :: Python :: 3
Classifier: Programming Language :: Python :: 3.7
Classifier: Programming Language :: Python :: 3.8
Classifier: Programming Language :: Python :: 3.9
Classifier: Programming Language :: Python :: 3.10
Classifier: Programming Language :: Python :: 3.11
Classifier: Topic :: Scientific/Engineering :: Information Analysis
Classifier: Topic :: Software Development :: Libraries :: Python Modules
Requires-Python: >=3.7
License-File: LICENSE
Requires-Dist: numpy>=1.19.0
Requires-Dist: pandas>=1.0.0
Requires-Dist: openpyxl>=3.0.0
Dynamic: author
Dynamic: home-page
Dynamic: license-file
Dynamic: requires-python
